kotadb/__init__.py
kotadb/builders.py
kotadb/client.py
kotadb/exceptions.py
kotadb/server.py
kotadb/types.py
kotadb/validated_types.py
kotadb/validation.py
tests/__init__.py
tests/test_benchmark.py
tests/test_builders.py
tests/test_client.py
tests/test_integration.py
tests/test_property.py
tests/test_server.py
tests/test_server_real.py
tests/test_stress.py
tests/test_validated_types.py
kotadb_client-0.6.1.dist-info/METADATA
kotadb_client-0.6.1.dist-info/WHEEL
kotadb_client-0.6.1.dist-info/top_level.txt
kotadb_client-0.6.1.dist-info/RECORD
